[{"data":{"id":"PublishDocs","source":null,"target":null}},{"data":{"id":"53eeb375-3223-46ed-9600-c30a2920fee8","source":"PublishDocs","target":"Force-Publish-Documentation"}},{"data":{"id":"Force-Publish-Documentation","source":null,"target":null}},{"data":{"id":"e77c5fca-1032-4be7-aa91-df93df1e9a55","source":"Force-Publish-Documentation","target":"Clean-Documentation"}},{"data":{"id":"04416f63-b6eb-47ac-b88f-15b1dc21562a","source":"Force-Publish-Documentation","target":"Deploy-Graph-Documentation"}},{"data":{"id":"Deploy-Graph-Documentation","source":null,"target":null}},{"data":{"id":"Clean-Documentation","source":null,"target":null}}]